Workbook
Name CEPCI_ref: [1]Calculations!$C$28
Name CEPCI2014: [1]Calculations!$C$22
Name CEPCI2015: [1]Calculations!$C$23
Name DE2014_: [1]Calculations!$C$8

Sheet Data_base_case
A1: Red: Don't change the name without changing the Julia code | F1: Used (1 or 0) | G1: Capacity units | H1: Output units | I1: Yearly demand (output) | J1: Produced from | K1: El balance | L1: Heat balance | M1: H2 balance | N1: Max Capacity | O1: Fuel production rate (kg output/kg input) | P1: Heat generated (kWh/output) | Q1: Load min (% of max capacity) | R1: Ramp up (% of capacity /h) | S1: Ramp down (% of capacity /h) | T1: Electrical consumption (kWh/output) | U1: Investment (EUR/Capacity installed) | V1: Fixed cost (EUR/Capacity installed/y) | W1: Variable cost (EUR/output) | X1: Fuel selling price (EUR/output) | Y1: Fuel buying price (EUR/output) | Z1: Annuity factor
B2: Subsets | C2: Subsets_2 | D2: Type of units | E2: Parameters--> | F2: =F1 -> Used (1 or 0) | G2: =G1 -> Capacity units | H2: =H1 -> Output units | I2: =I1 -> Yearly demand (output) | J2: =J1 -> Produced from | K2: =K1 -> El balance | L2: =L1 -> Heat balance | M2: =M1 -> H2 balance | ... Z2: =Z1 -> Annuity factor
E3: Year--> | F3: All | G3: All | H3: All | I3: All | J3: All | K3: All | L3: All | M3: All | N3: All | O3: 2020 | P3: 2020 | Q3: 2020 | R3: 2020 | S3: 2020 | T3: 2020 | U3: 2020 | V3: 2020 | W3: 2020 | X3: 2020 | Y3: 2020 | Z3: 2020
F4: =F2&F3 -> Used (1 or 0)All | G4: =G2&G3 -> Capacity unitsAll | H4: =H2&H3 -> Output unitsAll | I4: =I2&I3 -> Yearly demand (output)All | J4: =J2&J3 -> Produced fromAll | K4: =K2&K3 -> El balanceAll | L4: =L2&L3 -> Heat balanceAll | M4: =M2&M3 -> H2 balanceAll | ... T4: =T2&T3 -> Electrical consumption (kWh/output)2020 | U4: Investment (EUR/Capacity installed)2025 bench | V4: =V2&V3 -> Fixed cost (EUR/Capacity installed/y)2020 | W4: =W2&W3 -> Variable cost (EUR/output)2020 | X4: =X2&X3 -> Fuel selling price (EUR/output)2020 | Y4: =Y2&Y3 -> Fuel buying price (EUR/output)2020 | Z4: =Z2&Z3 -> Annuity factor2020
E5: Line/Column index | F5: =COLUMN(F2)-COLUMN($E$5) -> 1 | G5: =COLUMN(G2)-COLUMN($E$5) -> 2 | H5: =COLUMN(H2)-COLUMN($E$5) -> 3 | I5: =COLUMN(I2)-COLUMN($E$5) -> 4 | J5: =COLUMN(J2)-COLUMN($E$5) -> 5 | K5: =COLUMN(K2)-COLUMN($E$5) -> 6 | L5: =COLUMN(L2)-COLUMN($E$5) -> 7 | M5: =COLUMN(M2)-COLUMN($E$5) -> 8 | ... T5: =COLUMN(T2)-COLUMN($E$5) -> 15 | U5: 17 | V5: =COLUMN(V2)-COLUMN($E$5) -> 17 | W5: =COLUMN(W2)-COLUMN($E$5) -> 18 | X5: =COLUMN(X2)-COLUMN($E$5) -> 19 | Y5: =COLUMN(Y2)-COLUMN($E$5) -> 20 | Z5: =COLUMN(Z2)-COLUMN($E$5) -> 21
A6: Non-electrical | B6: Product | C6: Min_demand_MainFuel | D6: NH3 plant + ASU with AEC | E6: =ROW(D6)-ROW($E$5) -> 1 | F6: 1 | G6: kgNH3/h | H6: kgNH3 | I6: =430*10^6 -> 430000000 | J6: =B11 -> Reactant3 | K6: 0 | L6: 1 | M6: 0 | N6: 20000 | O6: 5.2910053 | P6: 0 | Q6: 0.4 | R6: 0.2 | S6: 0.2 | T6: 0.38 | U6: 4192 | V6: 436 | W6: 0 | X6: 0 | Y6: 0 | Z6: 0.093678779
B7: Product | C7: Min_demand_MainFuel | D7: NH3 plant + ASU with SOEC | E7: =ROW(D7)-ROW($E$5) -> 2 | F7: 1 | G7: kgNH3/h | H7: kgNH3 | I7: =430*10^6 -> 430000000 | J7: =B11 -> Reactant3 | K7: 0 | L7: 1 | M7: 0 | N7: =N6 -> 20000 | O7: 5.2910053 | P7: 0 | Q7: 0.4 | R7: 0.2 | S7: 0.2 | T7: 0.83 | U7: 4192 | V7: 828 | W7: 0 | X7: 0 | Y7: 0 | Z7: 0.093678779
B8: Reactant1 | C8: NoSubset | D8: Water supply (desalination plant) | E8: =ROW(D8)-ROW($E$5) -> 3 | F8: 1 | G8: kgH2O/h | H8: kgH2O | I8: 0 | J8: - | K8: 0 | L8: 0 | M8: 0 | N8: 400000 | O8: 0 | P8: 0 | Q8: 0 | R8: 1 | S8: 1 | T8: 0.004 | U8: 26.145192 | V8: 0 | W8: 0.00025895169 | X8: 0 | Y8: 0 | Z8: 0.10185221
B9: Product/Reactant2 | C9: NoSubset | D9: Electrolysers AEC | E9: =ROW(D9)-ROW($E$5) -> 4 | F9: 1 | G9: kgH2/h | H9: kgH2 | I9: 0 | J9: =B8 -> Reactant1 | K9: 0 | L9: 1 | M9: 1 | N9: 20000 | O9: 0.067 | P9: 7.07 | Q9: 0 | R9: 1 | S9: 1 | T9: 51.5 | U9: 56467 | V9: 1129 | W9: 0 | X9: 0 | Y9: 0 | Z9: 0.093678779
B10: Product/Reactant2 | C10: NoSubset | D10: Electrolysers SOEC heat integrated | E10: =ROW(D10)-ROW($E$5) -> 5 | F10: 1 | G10: kgH2/h | H10: kgH2 | I10: 0 | J10: =B8 -> Reactant1 | K10: 0 | L10: 1 | M10: 1 | N10: =N9 -> 20000 | O10: 0.067 | P10: 0 | Q10: 0 | R10: 1 | S10: 1 | T10: 37.9 | U10: 131493 | V10: 3945 | W10: 0 | X10: 0 | Y10: 0 | Z10: 0.093678779
B11: Reactant3 | C11: NoSubset | D11: H2 pipeline to NH3 plant | E11: =ROW(D11)-ROW($E$5) -> 6 | F11: 1 | G11: kgH2/h | H11: kgH2 | I11: 0 | J11: - | K11: 0 | L11: 0 | M11: -1 | N11: =N9 -> 20000 | O11: 0 | P11: 0 | Q11: 0 | R11: 1 | S11: 1 | T11: 0 | U11: 0 | V11: 0 | W11: 0 | X11: 0 | Y11: 0 | Z11: 0
B12: Product | C12: O2_sell | D12: Sale of oxygen | E12: =ROW(D12)-ROW($E$5) -> 7 | F12: 1 | G12: kgO2/h | H12: kgO2 | I12: 0 | J12: =B9 -> Product/Reactant2 | K12: 0 | L12: 0 | M12: 0 | N12: =9*N9 -> 180000 | O12: 7.76 | P12: 0 | Q12: 0 | R12: 1 | S12: 1 | T12: 0 | U12: 0 | V12: 0 | W12: 0 | X12: 0.05 | Y12: 0 | Z12: 0
B13: Heat_in | C13: NoSubset | D13: Heat from district heating | E13: =ROW(D13)-ROW($E$5) -> 8 | F13: 1 | G13: kWth | H13: kWhth | I13: 0 | J13: - | K13: 0 | L13: 1 | M13: 0 | N13: =N18 -> 2000000 | O13: 0 | P13: 0 | Q13: 0 | R13: 1 | S13: 1 | T13: 0 | U13: 0 | V13: 0 | W13: 0 | X13: 0 | Y13: 0 | Z13: 0
B14: Heat_out | C14: Heat_sell | D14: Heat sent to district heating | E14: =ROW(D14)-ROW($E$5) -> 9 | F14: 1 | G14: kWth | H14: kWhth | I14: 0 | J14: - | K14: 0 | L14: -1 | M14: 0 | N14: =N18 -> 2000000 | O14: 0 | P14: 1 | Q14: 0 | R14: 1 | S14: 1 | T14: 0 | U14: 0 | V14: 0 | W14: 0 | X14: 0.023 | Y14: 0 | Z14: 0
B15: Stor_in | C15: NoSubset | D15: H2 storage compressor | E15: =ROW(D15)-ROW($E$5) -> 10 | F15: 1 | G15: kgH2/h | H15: kgH2 | I15: 0 | J15: - | K15: 0 | L15: 0 | M15: -1 | N15: 20000 | O15: 0 | P15: 0 | Q15: 0 | R15: 1 | S15: 1 | T15: 0.94 | U15: 0 | V15: 0 | W15: 0 | X15: 0 | Y15: 0 | Z15: 0.093678779
B16: Stor_out | C16: NoSubset | D16: H2 storage valve | E16: =ROW(D16)-ROW($E$5) -> 11 | F16: 1 | G16: kgH2/h | H16: kgH2 | I16: 0 | J16: - | K16: 0 | L16: 0 | M16: 1 | N16: 20000 | O16: 0 | P16: 0 | Q16: 0 | R16: 1 | S16: 1 | T16: 0 | U16: 0 | V16: 0 | W16: 0 | X16: 0 | Y16: 0 | Z16: 0
B17: Tank | C17: NoSubset | D17: H2 storage (buried pipes) | E17: =ROW(D17)-ROW($E$5) -> 12 | F17: 1 | G17: kgH2 | H17: kgH2 | I17: 0 | J17: - | K17: 0 | L17: 0 | M17: 0 | N17: 20000000 | O17: 0 | P17: 0 | Q17: 0.09 | R17: 1 | S17: 1 | T17: 0 | U17: 460.75542 | V17: 0.99167601 | W17: 0 | X17: 0 | Y17: 0 | Z17: 0.081742858
A18: Electrical | B18: RPU_Solar_fixed | C18: NoSubset | D18: Solar fixed | E18: =ROW(D18)-ROW($E$5) -> 13 | F18: 1 | G18: kWe | H18: kWhe | I18: 0 | J18: - | K18: 1 | L18: 0 | M18: 0 | N18: 2000000 | O18: 0 | P18: 0 | Q18: 0 | R18: 1 | S18: 1 | T18: 0 | U18: 552.6787 | V18: 9.1244125 | W18: 0 | X18: 0 | Y18: 0 | Z18: 0.085803265
B19: RPU_Solar_track | C19: NoSubset | D19: Solar tracking | E19: =ROW(D19)-ROW($E$5) -> 14 | F19: 1 | G19: kWe | H19: kWhe | I19: 0 | J19: - | K19: 1 | L19: 0 | M19: 0 | N19: =$N$18 -> 2000000 | O19: 0 | P19: 0 | Q19: 0 | R19: 1 | S19: 1 | T19: 0 | U19: 646.5298 | V19: 11.157853 | W19: 0 | X19: 0 | Y19: 0 | Z19: 0.085803265
B20: =CONCATENATE("RPU_"&D20) -> RPU_ON_SP198-HH100 | C20: NoSubset | D20: ON_SP198-HH100 | E20: =ROW(D20)-ROW($E$5) -> 15 | F20: 1 | G20: kWe | H20: kWhe | I20: 0 | J20: - | K20: 1 | L20: 0 | M20: 0 | N20: =$N$18 -> 2000000 | O20: 0 | P20: 0 | Q20: 0 | R20: 1 | S20: 1 | T20: 0 | U20: 1758.6808 | V20: 14.59906 | W20: 0.001564185 | X20: 0 | Y20: 0 | Z20: 0.091448096
B21: =CONCATENATE("RPU_"&D21) -> RPU_ON_SP198-HH150 | C21: NoSubset | D21: ON_SP198-HH150 | E21: =ROW(D21)-ROW($E$5) -> 16 | F21: 1 | G21: kWe | H21: kWhe | I21: 0 | J21: - | K21: 1 | L21: 0 | M21: 0 | N21: =$N$18 -> 2000000 | O21: 0 | P21: 0 | Q21: 0 | R21: 1 | S21: 1 | T21: 0 | U21: 2188.7934 | V21: 14.59906 | W21: 0.001564185 | X21: 0 | Y21: 0 | Z21: 0.091448096
B22: =CONCATENATE("RPU_"&D22) -> RPU_ON_SP237-HH100 | C22: NoSubset | D22: ON_SP237-HH100 | E22: =ROW(D22)-ROW($E$5) -> 17 | F22: 1 | G22: kWe | H22: kWhe | I22: 0 | J22: - | K22: 1 | L22: 0 | M22: 0 | N22: =$N$18 -> 2000000 | O22: 0 | P22: 0 | Q22: 0 | R22: 1 | S22: 1 | T22: 0 | U22: 1554.7628 | V22: 14.59906 | W22: 0.001564185 | X22: 0 | Y22: 0 | Z22: 0.091448096
B23: =CONCATENATE("RPU_"&D23) -> RPU_ON_SP237-HH150 | C23: NoSubset | D23: ON_SP237-HH150 | E23: =ROW(D23)-ROW($E$5) -> 18 | F23: 1 | G23: kWe | H23: kWhe | I23: 0 | J23: - | K23: 1 | L23: 0 | M23: 0 | N23: =$N$18 -> 2000000 | O23: 0 | P23: 0 | Q23: 0 | R23: 1 | S23: 1 | T23: 0 | U23: 1947.4739 | V23: 14.59906 | W23: 0.001564185 | X23: 0 | Y23: 0 | Z23: 0.091448096
B24: =CONCATENATE("RPU_"&D24) -> RPU_ON_SP277-HH100 | C24: NoSubset | D24: ON_SP277-HH100 | E24: =ROW(D24)-ROW($E$5) -> 19 | F24: 1 | G24: kWe | H24: kWhe | I24: 0 | J24: - | K24: 1 | L24: 0 | M24: 0 | N24: =$N$18 -> 2000000 | O24: 0 | P24: 0 | Q24: 0 | R24: 1 | S24: 1 | T24: 0 | U24: 1414.9829 | V24: 14.59906 | W24: 0.001564185 | X24: 0 | Y24: 0 | Z24: 0.091448096
B25: =CONCATENATE("RPU_"&D25) -> RPU_ON_SP277-HH150 | C25: NoSubset | D25: ON_SP277-HH150 | E25: =ROW(D25)-ROW($E$5) -> 20 | F25: 1 | G25: kWe | H25: kWhe | I25: 0 | J25: - | K25: 1 | L25: 0 | M25: 0 | N25: =$N$18 -> 2000000 | O25: 0 | P25: 0 | Q25: 0 | R25: 1 | S25: 1 | T25: 0 | U25: 1807.694 | V25: 14.59906 | W25: 0.001564185 | X25: 0 | Y25: 0 | Z25: 0.091448096
B26: =CONCATENATE("RPU_"&D26) -> RPU_ON_SP321-HH100 | C26: NoSubset | D26: ON_SP321-HH100 | E26: =ROW(D26)-ROW($E$5) -> 21 | F26: 1 | G26: kWe | H26: kWhe | I26: 0 | J26: - | K26: 1 | L26: 0 | M26: 0 | N26: =$N$18 -> 2000000 | O26: 0 | P26: 0 | Q26: 0 | R26: 1 | S26: 1 | T26: 0 | U26: 1301.2948 | V26: 14.59906 | W26: 0.001564185 | X26: 0 | Y26: 0 | Z26: 0.091448096
B27: =CONCATENATE("RPU_"&D27) -> RPU_ON_SP321-HH150 | C27: NoSubset | D27: ON_SP321-HH150 | E27: =ROW(D27)-ROW($E$5) -> 22 | F27: 1 | G27: kWe | H27: kWhe | I27: 0 | J27: - | K27: 1 | L27: 0 | M27: 0 | N27: =$N$18 -> 2000000 | O27: 0 | P27: 0 | Q27: 0 | R27: 1 | S27: 1 | T27: 0 | U27: 1694.0063 | V27: 14.59906 | W27: 0.001564185 | X27: 0 | Y27: 0 | Z27: 0.091448096
B28: =CONCATENATE("RPU_"&D28) -> RPU_OFF_SP379-HH100 | C28: NoSubset | D28: OFF_SP379-HH100 | E28: =ROW(D28)-ROW($E$5) -> 23 | F28: 1 | G28: kWe | H28: kWhe | I28: 0 | J28: - | K28: 1 | L28: 0 | M28: 0 | N28: =$N$18 -> 2000000 | O28: 0 | P28: 0 | Q28: 0 | R28: 1 | S28: 1 | T28: 0 | U28: 2205.1904 | V28: 41.773125 | W28: 0.00312837 | X28: 0 | Y28: 0 | Z28: 0.091448096
B29: =CONCATENATE("RPU_"&D29) -> RPU_OFF_SP379-HH150 | C29: NoSubset | D29: OFF_SP379-HH150 | E29: =ROW(D29)-ROW($E$5) -> 24 | F29: 1 | G29: kWe | H29: kWhe | I29: 0 | J29: - | K29: 1 | L29: 0 | M29: 0 | N29: =$N$18 -> 2000000 | O29: 0 | P29: 0 | Q29: 0 | R29: 1 | S29: 1 | T29: 0 | U29: 2534.6072 | V29: 41.773125 | W29: 0.00312837 | X29: 0 | Y29: 0 | Z29: 0.091448096
B30: =CONCATENATE("RPU_"&D30) -> RPU_OFF_SP450-HH100 | C30: NoSubset | D30: OFF_SP450-HH100 | E30: =ROW(D30)-ROW($E$5) -> 25 | F30: 1 | G30: kWe | H30: kWhe | I30: 0 | J30: - | K30: 1 | L30: 0 | M30: 0 | N30: =$N$18 -> 2000000 | O30: 0 | P30: 0 | Q30: 0 | R30: 1 | S30: 1 | T30: 0 | U30: 1988.1235 | V30: 41.773125 | W30: 0.00312837 | X30: 0 | Y30: 0 | Z30: 0.091448096
B31: =CONCATENATE("RPU_"&D31) -> RPU_OFF_SP450-HH150 | C31: NoSubset | D31: OFF_SP450-HH150 | E31: =ROW(D31)-ROW($E$5) -> 26 | F31: 1 | G31: kWe | H31: kWhe | I31: 0 | J31: - | K31: 1 | L31: 0 | M31: 0 | N31: =$N$18 -> 2000000 | O31: 0 | P31: 0 | Q31: 0 | R31: 1 | S31: 1 | T31: 0 | U31: 2265.527 | V31: 41.773125 | W31: 0.00312837 | X31: 0 | Y31: 0 | Z31: 0.091448096
B32: PU_Grid_in | C32: Grid_buy | D32: Electricity from the grid | E32: =ROW(D32)-ROW($E$5) -> 27 | F32: 1 | G32: kWe | H32: kWhe | I32: 0 | J32: - | K32: 1 | L32: 0 | M32: 0 | N32: =$N$18 -> 2000000 | O32: 0 | P32: 0 | Q32: 0 | R32: 1 | S32: 1 | T32: 0 | U32: 66 | V32: 0 | W32: 0 | X32: 0 | Y32: 0.01665 | Z32: 0.085803265
B33: Grid_out | C33: NoSubset | D33: Curtailment | E33: =ROW(D33)-ROW($E$5) -> 28 | F33: 1 | G33: kWe | H33: kWhe | I33: 0 | J33: - | K33: -1 | L33: 0 | M33: 0 | N33: 24000 | O33: 0 | P33: 0 | Q33: 0 | R33: 1 | S33: 1 | T33: 0 | U33: 0 | V33: 0 | W33: 0 | X33: 0 | Y33: 0 | Z33: 0
B34: Stor_in | C34: NoSubset | D34: Charge batteries | E34: =ROW(D34)-ROW($E$5) -> 29 | F34: 1 | G34: kWe | H34: kWhe | I34: 0 | J34: - | K34: -1 | L34: 0 | M34: 0 | N34: =N36/2 -> 10000000 | O34: 0 | P34: 0 | Q34: 0 | R34: 1 | S34: 1 | T34: 0.04 | U34: 0 | V34: 0 | W34: 0.00208558 | X34: 0 | Y34: 0 | Z34: 0
B35: Stor_out | C35: NoSubset | D35: Discharge batteries | E35: =ROW(D35)-ROW($E$5) -> 30 | F35: 1 | G35: kWe | H35: kWhe | I35: 0 | J35: - | K35: 1 | L35: 0 | M35: 0 | N35: =3*N36 -> 60000000 | O35: 0 | P35: 0 | Q35: 0 | R35: 1 | S35: 1 | T35: 0.05 | U35: 0 | V35: 0 | W35: 0 | X35: 0 | Y35: 0 | Z35: 0
B36: Tank | C36: NoSubset | D36: Batteries | E36: =ROW(D36)-ROW($E$5) -> 31 | F36: 1 | G36: kWhe | H36: kWhe | I36: 0 | J36: - | K36: 0 | L36: 0 | M36: 0 | N36: 20000000 | O36: 0 | P36: 0 | Q36: 0.2 | R36: 1 | S36: 1 | T36: 0 | U36: 361.82973 | V36: 5.0761 | W36: 0 | X36: 0 | Y36: 0 | Z36: 0.10185221

Sheet Selected_units
B1: Fuel produced | C1: NH3 | D1: NH3
B2: Fuel energy content LHV (MJ/kg fuel) | C2: 18.6 | D2: 18.6
B3: Electrolyser | C3: AEC | D3: SOEC
B4: Carbon capture | C4: None | D4: None
B5: Configuration | C5: =C1&"_"&C3&"_"&C4 -> NH3_AEC_None | D5: =D1&"_"&D3&"_"&D4 -> NH3_SOEC_None
A6: =ROW(B6)-ROW($A$5) -> 1 | B6: =Data_base_case!D6 -> NH3 plant + ASU with AEC | C6: =IF(AND(C1="NH3",C3="AEC"),1,0) -> 1 | D6: =IF(AND(D1="NH3",D3="AEC"),1,0) -> 0
A7: =ROW(B7)-ROW($A$5) -> 2 | B7: =Data_base_case!D7 -> NH3 plant + ASU with SOEC | C7: =IF(AND(C1="NH3",C3<>"AEC"),1,0) -> 0 | D7: =IF(AND(D1="NH3",D3<>"AEC"),1,0) -> 1
A8: =ROW(B8)-ROW($A$5) -> 3 | B8: =Data_base_case!D8 -> Water supply (desalination plant) | C8: 1 | D8: 1
A9: =ROW(B9)-ROW($A$5) -> 4 | B9: =Data_base_case!D9 -> Electrolysers AEC | C9: =IF(C3="AEC",1,0) -> 1 | D9: =IF(D3="AEC",1,0) -> 0
A10: =ROW(B10)-ROW($A$5) -> 5 | B10: =Data_base_case!D10 -> Electrolysers SOEC heat integrated | C10: =IF(AND(C3="SOEC",OR(C1="Bio-eMeOH",C1="NH3")),1,0) -> 0 | D10: =IF(AND(D3="SOEC",OR(D1="Bio-eMeOH",D1="NH3")),1,0) -> 1
A11: =ROW(B11)-ROW($A$5) -> 6 | B11: =Data_base_case!D11 -> H2 pipeline to NH3 plant | C11: =IF(C1 = "NH3",1,0) -> 1 | D11: =IF(D1 = "NH3",1,0) -> 1
A12: =ROW(B12)-ROW($A$5) -> 7 | B12: =Data_base_case!D13 -> Heat from district heating | C12: 1 | D12: 1
A13: =ROW(B13)-ROW($A$5) -> 8 | B13: =Data_base_case!D14 -> Heat sent to district heating | C13: 1 | D13: 1
A14: =ROW(B14)-ROW($A$5) -> 9 | B14: =Data_base_case!D12 -> Sale of oxygen | C14: 1 | D14: 1
A15: =ROW(B15)-ROW($A$5) -> 10 | B15: =Data_base_case!D15 -> H2 storage compressor | C15: =C17 -> 1 | D15: =D17 -> 1
A16: =ROW(B16)-ROW($A$5) -> 11 | B16: =Data_base_case!D16 -> H2 storage valve | C16: =C17 -> 1 | D16: =D17 -> 1
A17: =ROW(B17)-ROW($A$5) -> 12 | B17: =Data_base_case!D17 -> H2 storage (buried pipes) | C17: 1 | D17: 1
A18: =ROW(B18)-ROW($A$5) -> 13 | B18: =Data_base_case!D18 -> Solar fixed | C18: 1 | D18: 1
A19: =ROW(B19)-ROW($A$5) -> 14 | B19: =Data_base_case!D19 -> Solar tracking | C19: 1 | D19: 1
A20: =ROW(B20)-ROW($A$5) -> 15 | B20: =Data_base_case!D20 -> ON_SP198-HH100 | C20: 1 | D20: 1
A21: =ROW(B21)-ROW($A$5) -> 16 | B21: =Data_base_case!D21 -> ON_SP198-HH150 | C21: 1 | D21: 1
A22: =ROW(B22)-ROW($A$5) -> 17 | B22: =Data_base_case!D22 -> ON_SP237-HH100 | C22: 1 | D22: 1
A23: =ROW(B23)-ROW($A$5) -> 18 | B23: =Data_base_case!D23 -> ON_SP237-HH150 | C23: 1 | D23: 1
A24: =ROW(B24)-ROW($A$5) -> 19 | B24: =Data_base_case!D24 -> ON_SP277-HH100 | C24: 1 | D24: 1
A25: =ROW(B25)-ROW($A$5) -> 20 | B25: =Data_base_case!D25 -> ON_SP277-HH150 | C25: 1 | D25: 1
A26: =ROW(B26)-ROW($A$5) -> 21 | B26: =Data_base_case!D26 -> ON_SP321-HH100 | C26: 1 | D26: 1
A27: =ROW(B27)-ROW($A$5) -> 22 | B27: =Data_base_case!D27 -> ON_SP321-HH150 | C27: 1 | D27: 1
A28: =ROW(B28)-ROW($A$5) -> 23 | B28: =Data_base_case!D28 -> OFF_SP379-HH100 | C28: 1 | D28: 1
... A33: =ROW(B33)-ROW($A$5) -> 28 | B33: =Data_base_case!D33 -> Curtailment | C33: 1 | D33: 1
A34: =ROW(B34)-ROW($A$5) -> 29 | B34: =Data_base_case!D34 -> Charge batteries | C34: =C36 -> 1 | D34: =D36 -> 1
A35: =ROW(B35)-ROW($A$5) -> 30 | B35: =Data_base_case!D35 -> Discharge batteries | C35: =C36 -> 1 | D35: =D36 -> 1
A36: =ROW(B36)-ROW($A$5) -> 31 | B36: =Data_base_case!D36 -> Batteries | C36: 1 | D36: 1

Sheet Scenarios_definition
A1: Changes also include the changes made in the reference scenario. If nothing is specified in the reference scenario column, changes are made compared to the input data sheet (i.e Data_base_case)
A2: Change are made compared to the reference scenario. "Chains" of reference scenarios doesn't work.
A4: Reference scenario | B4: Scenario name definition | C4: Type of units for change | D4: Parameter changed | E4: Year new value | F4: New value | G4: Year old value | H4: Old value
B5: Semi-islanded | C5: Electricity from the grid | D5: =Data_base_case!$F$1 -> Used (1 or 0) | E5: All | F5: 1 | G5: All | H5: =INDEX(Data_base_case!$D$5:$Z$82,MATCH(Scenarios_definition!C5,Data_base_case!$D$5:$D$82,0),MATCH(Scenarios_definition!D5&Scenarios_definition!G5,Data_base_case!$D$4:$Z$4,0)) -> 1
A6: =B5 -> Semi-islanded | B6: Semi-islandedflex | C6: NH3 plant + ASU with AEC | D6: =Data_base_case!$Q$1 -> Load min (% of max capacity) | E6: All | F6: 0 | G6: 2020 | H6: =INDEX(Data_base_case!$D$5:$Z$82,MATCH(Scenarios_definition!C6,Data_base_case!$D$5:$D$82,0),MATCH(Scenarios_definition!D6&Scenarios_definition!G6,Data_base_case!$D$4:$Z$4,0)) -> 0.4
B7: Islanded | C7: =Data_base_case!D32 -> Electricity from the grid | D7: =Data_base_case!$F$1 -> Used (1 or 0) | E7: All | F7: 0 | G7: All | H7: =INDEX(Data_base_case!$D$5:$Z$82,MATCH(Scenarios_definition!C7,Data_base_case!$D$5:$D$82,0),MATCH(Scenarios_definition!D7&Scenarios_definition!G7,Data_base_case!$D$4:$Z$4,0)) -> 1
A8: Islanded | B8: Is_nonflex | C8: NH3 plant + ASU with AEC | D8: =Data_base_case!$Q$1 -> Load min (% of max capacity) | E8: All | F8: 1 | G8: 2020 | H8: =INDEX(Data_base_case!$D$5:$Z$82,MATCH(Scenarios_definition!C8,Data_base_case!$D$5:$D$82,0),MATCH(Scenarios_definition!D8&Scenarios_definition!G8,Data_base_case!$D$4:$Z$4,0)) -> 0.4
B9: SI_nonflex | C9: NH3 plant + ASU with AEC | D9: =Data_base_case!$Q$1 -> Load min (% of max capacity) | E9: All | F9: 1 | G9: 2020 | H9: =INDEX(Data_base_case!$D$5:$Z$82,MATCH(Scenarios_definition!C9,Data_base_case!$D$5:$D$82,0),MATCH(Scenarios_definition!D9&Scenarios_definition!G9,Data_base_case!$D$4:$Z$4,0)) -> 0.4
A10: Islanded | B10: Is_flex | C10: NH3 plant + ASU with AEC | D10: =Data_base_case!$Q$1 -> Load min (% of max capacity) | E10: All | F10: 0 | G10: 2020 | H10: =INDEX(Data_base_case!$D$5:$Z$82,MATCH(Scenarios_definition!C10,Data_base_case!$D$5:$D$82,0),MATCH(Scenarios_definition!D10&Scenarios_definition!G10,Data_base_case!$D$4:$Z$4,0)) -> 0.4

Sheet ScenariosToRun
B1: Options available
B2: Name of the scenario in the output csv file | C2: See Scenarios_definition | D2: Esbjerg | E2: NH3 | F2: None | G2: 2020 | H2: Name of the excel file profile | I2: AEC | J2: Any data sheet name | K2: Any name
D3: Ceduna | I3: SOEC
D4: Arica
Q5: Results to write
A7: Scenario number | B7: Scenario name | C7: Scenario | D7: Location | E7: Fuel | F7: CO2 capture | G7: Year data | H7: Profile name | I7: Electrolyser | J7: Input data sheet | K7: Result folder name | L7: Max capacity | M7: Ramping | N7: No negative elec price | O7: Fixed heat sale | P7: Fixed oxygen sale | Q7: Flows | R7: Sold products | S7: Fuel cost
A8: =ROW(A8)-ROW($A$7) -> 1 | B8: Behind-the-meter | C8: Islanded | D8: Esbjerg | E8: NH3 | F8: None | G8: 2020 | H8: ="2019" -> 2019 | I8: AEC | J8: Data_base_case | K8: Results_base_case | L8: FALSE | M8: FALSE | N8: TRUE | O8: FALSE | P8: FALSE | Q8: TRUE | R8: TRUE | S8: TRUE
A9: =ROW(A9)-ROW($A$7) -> 2 | B9: Behind-the-meter | C9: Islanded | D9: Ceduna | E9: NH3 | F9: None | G9: 2020 | H9: ="2019" -> 2019 | I9: AEC | J9: Data_base_case | K9: Results_base_case | L9: FALSE | M9: FALSE | N9: TRUE | O9: FALSE | P9: FALSE | Q9: TRUE | R9: TRUE | S9: TRUE
A10: =ROW(A10)-ROW($A$7) -> 3 | B10: Behind-the-meter | C10: Islanded | D10: Arica | E10: NH3 | F10: None | G10: 2020 | H10: ="2019" -> 2019 | I10: AEC | J10: Data_base_case | K10: Results_base_case | L10: FALSE | M10: FALSE | N10: TRUE | O10: FALSE | P10: FALSE | Q10: TRUE | R10: TRUE | S10: TRUE
A11: =ROW(A11)-ROW($A$7) -> 4 | B11: Base_case | C11: Semi-islanded | D11: Esbjerg | E11: NH3 | F11: None | G11: 2020 | H11: ="2019" -> 2019 | I11: AEC | J11: Data_base_case | K11: Results_base_case | L11: FALSE | M11: FALSE | N11: TRUE | O11: FALSE | P11: FALSE | Q11: TRUE | R11: TRUE | S11: TRUE
A12: =ROW(A12)-ROW($A$7) -> 5 | B12: Base_case | C12: Semi-islanded | D12: Ceduna | E12: NH3 | F12: None | G12: 2020 | H12: ="2019" -> 2019 | I12: AEC | J12: Data_base_case | K12: Results_base_case | L12: FALSE | M12: FALSE | N12: TRUE | O12: FALSE | P12: FALSE | Q12: TRUE | R12: TRUE | S12: TRUE
A13: =ROW(A13)-ROW($A$7) -> 6 | B13: Base_case | C13: Semi-islanded | D13: Arica | E13: NH3 | F13: None | G13: 2020 | H13: ="2019" -> 2019 | I13: AEC | J13: Data_base_case | K13: Results_base_case | L13: FALSE | M13: FALSE | N13: TRUE | O13: FALSE | P13: FALSE | Q13: TRUE | R13: TRUE | S13: TRUE
A14: =ROW(A14)-ROW($A$7) -> 7 | B14: Base_case | C14: Semi-islanded | D14: Esbjerg | E14: NH3 | F14: None | G14: 2020 | H14: ="2019" -> 2019 | I14: SOEC | J14: Data_base_case | K14: Results_base_case | L14: FALSE | M14: FALSE | N14: TRUE | O14: FALSE | P14: FALSE | Q14: TRUE | R14: TRUE | S14: TRUE
A15: =ROW(A15)-ROW($A$7) -> 8 | B15: Base_case | C15: Semi-islanded | D15: Ceduna | E15: NH3 | F15: None | G15: 2020 | H15: ="2019" -> 2019 | I15: SOEC | J15: Data_base_case | K15: Results_base_case | L15: FALSE | M15: FALSE | N15: TRUE | O15: FALSE | P15: FALSE | Q15: TRUE | R15: TRUE | S15: TRUE
A16: =ROW(A16)-ROW($A$7) -> 9 | B16: Base_case | C16: Semi-islanded | D16: Arica | E16: NH3 | F16: None | G16: 2020 | H16: ="2019" -> 2019 | I16: SOEC | J16: Data_base_case | K16: Results_base_case | L16: FALSE | M16: FALSE | N16: TRUE | O16: FALSE | P16: FALSE | Q16: TRUE | R16: TRUE | S16: TRUE
A17: =ROW(A17)-ROW($A$7) -> 10 | B17: Bhm-nonflexible | C17: Is_nonflex | D17: Esbjerg | E17: NH3 | F17: None | G17: 2020 | H17: ="2019" -> 2019 | I17: AEC | J17: Data_base_case | K17: Results_sensitivities | L17: FALSE | M17: FALSE | N17: TRUE | O17: FALSE | P17: FALSE | Q17: TRUE | R17: TRUE | S17: TRUE
A18: =ROW(A18)-ROW($A$7) -> 11 | B18: Bhm-nonflexible | C18: Is_nonflex | D18: Ceduna | E18: NH3 | F18: None | G18: 2020 | H18: ="2019" -> 2019 | I18: AEC | J18: Data_base_case | K18: Results_sensitivities | L18: FALSE | M18: FALSE | N18: TRUE | O18: FALSE | P18: FALSE | Q18: TRUE | R18: TRUE | S18: TRUE
A19: =ROW(A19)-ROW($A$7) -> 12 | B19: Bhm-nonflexible | C19: Is_nonflex | D19: Arica | E19: NH3 | F19: None | G19: 2020 | H19: ="2019" -> 2019 | I19: AEC | J19: Data_base_case | K19: Results_sensitivities | L19: FALSE | M19: FALSE | N19: TRUE | O19: FALSE | P19: FALSE | Q19: TRUE | R19: TRUE | S19: TRUE
... A25: =ROW(A25)-ROW($A$7) -> 18 | B25: Bhm-superflexible | C25: Is_flex | D25: Arica | E25: NH3 | F25: None | G25: 2020 | H25: ="2019" -> 2019 | I25: AEC | J25: Data_base_case | K25: Results_sensitivities | L25: FALSE | M25: FALSE | N25: TRUE | O25: FALSE | P25: FALSE | Q25: TRUE | R25: TRUE | S25: TRUE
